dsproc/__init__.py
dsproc/message/__init__.py
dsproc/message/encode.py
dsproc/message/message.py
dsproc/message/symbol2bit.py
dsproc/sig/__init__.py
dsproc/sig/_sig.py
dsproc/sig/constellation.py
dsproc/sig/demod.py
dsproc/sig/mod.py
dsproc/sig/plot.py
dsproc/util/__init__.py
dsproc/util/utils.py
dsproc-0.1.1.dist-info/METADATA
dsproc-0.1.1.dist-info/WHEEL
dsproc-0.1.1.dist-info/licenses/LICENSE.txt
dsproc-0.1.1.dist-info/RECORD
