Metadata-Version: 2.3
Name: dsproc
Version: 0.1.1
Summary: dsproc: a powerful digital signals processing toolkit
Project-URL: Documentation, https://github.com/importThat/dsproc
Project-URL: Homepage, https://github.com/importThat/dsproc
Project-URL: Issues, https://github.com/importThat/dsproc/issues
Project-URL: Source, https://github.com/importThat/dsproc
Author: importThat
License: MIT License
Keywords: demodulation,dsp,gnu radio,modulation,radio,sdr,signal,wave
Classifier: Programming Language :: Python
Classifier: Programming Language :: Python :: 3.12
Classifier: Programming Language :: Python :: 3.13
Classifier: Programming Language :: Python :: Implementation :: CPython
Requires-Python: >=3.12
Requires-Dist: matplotlib>=3.8.4
Requires-Dist: numpy>=1.26.4
Requires-Dist: scipy>=1.13.0
